<?xml version="1.0" encoding="UTF-8" standalone="no"?>
<databaseChangeLog logicalFilePath="db/changelog/changeset/db.changeset-2.0.xml" xmlns="http://www.liquibase.org/xml/ns/dbchangelog"
                   xmlns:xsi="http://www.w3.org/2001/XMLSchema-instance"
                   xsi:schemaLocation="http://www.liquibase.org/xml/ns/dbchangelog http://www.liquibase.org/xml/ns/dbchangelog/dbchangelog-3.4.xsd">

    <changeSet id="1" author="Rostislav Dolbilov">
        <insert tableName="products">
            <column name="product_type" value="Laptop"/>
            <column name="series_number" value="K1022Y"/>
            <column name="manufacturer" value="Acer"/>
            <column name="quantity" value="1"/>
            <column name="addition_settings" value="Diagonal 14 inch"/>
        </insert>

        <insert tableName="products">
            <column name="product_type" value="Personal PC"/>
            <column name="series_number" value="K102AA"/>
            <column name="manufacturer" value="HP"/>
            <column name="quantity" value="1"/>
            <column name="addition_settings" value="Desktop"/>
        </insert>

        <insert tableName="products">
            <column name="product_type" value="Monitor"/>
            <column name="series_number" value="U702A7"/>
            <column name="manufacturer" value="XIAOMI"/>
            <column name="quantity" value="1"/>
            <column name="addition_settings" value="Diagonal 32 inch"/>
        </insert>

        <insert tableName="products">
            <column name="product_type" value="HHD"/>
            <column name="series_number" value="U7THRE"/>
            <column name="manufacturer" value="Toshiba"/>
            <column name="quantity" value="1"/>
            <column name="addition_settings" value="Disk space 1T"/>
        </insert>
    </changeSet>
</databaseChangeLog>
